pytest_skipuntil.py
pytest_skipuntil-0.2.0.dist-info/LICENSE
pytest_skipuntil-0.2.0.dist-info/METADATA
pytest_skipuntil-0.2.0.dist-info/WHEEL
pytest_skipuntil-0.2.0.dist-info/entry_points.txt
pytest_skipuntil-0.2.0.dist-info/top_level.txt
pytest_skipuntil-0.2.0.dist-info/RECORD
