Metadata-Version: 2.1
Name: pytest-skipuntil
Version: 0.2.0
Summary: A simple pytest plugin to skip flapping test with deadline
Home-page: https://github.com/bp72/pytest-skipuntil
Author: Pavel Bityukov
Author-email: pavleg.bityukov@gmail.com
Maintainer: Pavel Bityukov
Maintainer-email: pavleg.bityukov@gmail.com
License: MIT
Classifier: Development Status :: 4 - Beta
Classifier: Framework :: Pytest
Classifier: Intended Audience :: Developers
Classifier: Topic :: Software Development :: Testing
Classifier: Programming Language :: Python
Classifier: Programming Language :: Python :: 3
Classifier: Programming Language :: Python :: 3.8
Classifier: Programming Language :: Python :: 3.9
Classifier: Programming Language :: Python :: 3.10
Classifier: Programming Language :: Python :: 3.11
Classifier: Programming Language :: Python :: 3.12
Classifier: Programming Language :: Python :: 3 :: Only
Classifier: Programming Language :: Python :: Implementation :: CPython
Classifier: Operating System :: OS Independent
Classifier: License :: OSI Approved :: MIT License
Requires-Python: >=3.8
License-File: LICENSE
Requires-Dist: pytest >=3.8.0
